[
  {
    "Stationsname": "Bad Muskau",
    "Fr 04.07.": "3",
    "Sa 05.07.": "5",
    "So 06.07.": "5",
    "Mo 07.07.": "4",
    "Di 08.07.": "1"
  },
  {
    "Stationsname": "Klitzschen bei Torgau",
    "Fr 04.07.": "4",
    "Sa 05.07.": "5",
    "So 06.07.": "5",
    "Mo 07.07.": "4",
    "Di 08.07.": "1"
  },
  {
    "Stationsname": "Hoyerswerda",
    "Fr 04.07.": "3",
    "Sa 05.07.": "5",
    "So 06.07.": "5",
    "Mo 07.07.": "3",
    "Di 08.07.": "1"
  },
  {
    "Stationsname": "Leipzig/Halle (Flughafen)",
    "Fr 04.07.": "3",
    "Sa 05.07.": "3",
    "So 06.07.": "3",
    "Mo 07.07.": "3",
    "Di 08.07.": "1"
  },
  {
    "Stationsname": "Leipzig-Holzhausen",
    "Fr 04.07.": "3",
    "Sa 05.07.": "4",
    "So 06.07.": "3",
    "Mo 07.07.": "2",
    "Di 08.07.": "1"
  },
  {
    "Stationsname": "Oschatz",
    "Fr 04.07.": "4",
    "Sa 05.07.": "4",
    "So 06.07.": "4",
    "Mo 07.07.": "3",
    "Di 08.07.": "1"
  },
  {
    "Stationsname": "Görlitz",
    "Fr 04.07.": "3",
    "Sa 05.07.": "4",
    "So 06.07.": "4",
    "Mo 07.07.": "3",
    "Di 08.07.": "1"
  },
  {
    "Stationsname": "Kubschütz",
    "Fr 04.07.": "3",
    "Sa 05.07.": "4",
    "So 06.07.": "4",
    "Mo 07.07.": "3",
    "Di 08.07.": "1"
  },
  {
    "Stationsname": "Klipphausen-Garsebach",
    "Fr 04.07.": "2",
    "Sa 05.07.": "4",
    "So 06.07.": "4",
    "Mo 07.07.": "3",
    "Di 08.07.": "1"
  },
  {
    "Stationsname": "Dresden-Klotzsche (Flughafen)",
    "Fr 04.07.": "3",
    "Sa 05.07.": "4",
    "So 06.07.": "4",
    "Mo 07.07.": "3",
    "Di 08.07.": "1"
  },
  {
    "Stationsname": "Geringswalde-Altgeringswalde",
    "Fr 04.07.": "3",
    "Sa 05.07.": "3",
    "So 06.07.": "3",
    "Mo 07.07.": "3",
    "Di 08.07.": "1"
  },
  {
    "Stationsname": "Sohland/Spree",
    "Fr 04.07.": "3",
    "Sa 05.07.": "3",
    "So 06.07.": "3",
    "Mo 07.07.": "2",
    "Di 08.07.": "1"
  },
  {
    "Stationsname": "Nossen",
    "Fr 04.07.": "3",
    "Sa 05.07.": "3",
    "So 06.07.": "3",
    "Mo 07.07.": "3",
    "Di 08.07.": "1"
  },
  {
    "Stationsname": "Dresden-Hosterwitz",
    "Fr 04.07.": "3",
    "Sa 05.07.": "4",
    "So 06.07.": "4",
    "Mo 07.07.": "3",
    "Di 08.07.": "1"
  },
  {
    "Stationsname": "Lichtenhain-Mittelndorf",
    "Fr 04.07.": "3",
    "Sa 05.07.": "3",
    "So 06.07.": "3",
    "Mo 07.07.": "2",
    "Di 08.07.": "1"
  },
  {
    "Stationsname": "Dippoldiswalde-Reinberg",
    "Fr 04.07.": "3",
    "Sa 05.07.": "3",
    "So 06.07.": "3",
    "Mo 07.07.": "2",
    "Di 08.07.": "2"
  },
  {
    "Stationsname": "Bertsdorf-Hörnitz",
    "Fr 04.07.": "3",
    "Sa 05.07.": "3",
    "So 06.07.": "3",
    "Mo 07.07.": "2",
    "Di 08.07.": "1"
  },
  {
    "Stationsname": "Chemnitz",
    "Fr 04.07.": "3",
    "Sa 05.07.": "3",
    "So 06.07.": "3",
    "Mo 07.07.": "3",
    "Di 08.07.": "1"
  },
  {
    "Stationsname": "Zinnwald-Georgenfeld",
    "Fr 04.07.": "3",
    "Sa 05.07.": "3",
    "So 06.07.": "3",
    "Mo 07.07.": "2",
    "Di 08.07.": "1"
  },
  {
    "Stationsname": "Lichtentanne",
    "Fr 04.07.": "3",
    "Sa 05.07.": "3",
    "So 06.07.": "3",
    "Mo 07.07.": "3",
    "Di 08.07.": "1"
  },
  {
    "Stationsname": "Marienberg",
    "Fr 04.07.": "3",
    "Sa 05.07.": "3",
    "So 06.07.": "3",
    "Mo 07.07.": "2",
    "Di 08.07.": "1"
  },
  {
    "Stationsname": "Deutschneudorf-Brüderwiese",
    "Fr 04.07.": "3",
    "Sa 05.07.": "3",
    "So 06.07.": "3",
    "Mo 07.07.": "2",
    "Di 08.07.": "1"
  },
  {
    "Stationsname": "Aue",
    "Fr 04.07.": "3",
    "Sa 05.07.": "3",
    "So 06.07.": "3",
    "Mo 07.07.": "2",
    "Di 08.07.": "1"
  },
  {
    "Stationsname": "Treuen",
    "Fr 04.07.": "2",
    "Sa 05.07.": "3",
    "So 06.07.": "3",
    "Mo 07.07.": "2",
    "Di 08.07.": "1"
  },
  {
    "Stationsname": "Plauen",
    "Fr 04.07.": "3",
    "Sa 05.07.": "3",
    "So 06.07.": "3",
    "Mo 07.07.": "2",
    "Di 08.07.": "1"
  },
  {
    "Stationsname": "Carlsfeld",
    "Fr 04.07.": "2",
    "Sa 05.07.": "3",
    "So 06.07.": "3",
    "Mo 07.07.": "2",
    "Di 08.07.": "1"
  },
  {
    "Stationsname": "Bad Elster-Sohl",
    "Fr 04.07.": "3",
    "Sa 05.07.": "3",
    "So 06.07.": "3",
    "Mo 07.07.": "2",
    "Di 08.07.": "1"
  }
]