[
  {
    "Stationsname": "Weiskirchen/Saar",
    "Do 30.10.": "1",
    "Fr 31.10.": "1",
    "Sa 01.11.": "1",
    "So 02.11.": "1",
    "Mo 03.11.": "1"
  },
  {
    "Stationsname": "Perl-Nennig",
    "Do 30.10.": "1",
    "Fr 31.10.": "1",
    "Sa 01.11.": "1",
    "So 02.11.": "1",
    "Mo 03.11.": "1"
  },
  {
    "Stationsname": "Tholey",
    "Do 30.10.": "1",
    "Fr 31.10.": "1",
    "Sa 01.11.": "1",
    "So 02.11.": "1",
    "Mo 03.11.": "1"
  },
  {
    "Stationsname": "Neunkirchen-Wellesweiler",
    "Do 30.10.": "1",
    "Fr 31.10.": "1",
    "Sa 01.11.": "1",
    "So 02.11.": "1",
    "Mo 03.11.": "1"
  },
  {
    "Stationsname": "Berus",
    "Do 30.10.": "1",
    "Fr 31.10.": "1",
    "Sa 01.11.": "1",
    "So 02.11.": "1",
    "Mo 03.11.": "1"
  },
  {
    "Stationsname": "Saarbrücken-Burbach",
    "Do 30.10.": "1",
    "Fr 31.10.": "1",
    "Sa 01.11.": "1",
    "So 02.11.": "1",
    "Mo 03.11.": "1"
  },
  {
    "Stationsname": "Saarbrücken (Flughafen)",
    "Do 30.10.": "1",
    "Fr 31.10.": "1",
    "Sa 01.11.": "1",
    "So 02.11.": "1",
    "Mo 03.11.": "1"
  }
]