[
  {
    "Stationsname": "Arkona",
    "Di 02.09.": "1",
    "Mi 03.09.": "1",
    "Do 04.09.": "1",
    "Fr 05.09.": "1",
    "Sa 06.09.": "1"
  },
  {
    "Stationsname": "Insel Hiddensee",
    "Di 02.09.": "1",
    "Mi 03.09.": "1",
    "Do 04.09.": "2",
    "Fr 05.09.": "1",
    "Sa 06.09.": "1"
  },
  {
    "Stationsname": "Putbus",
    "Di 02.09.": "1",
    "Mi 03.09.": "1",
    "Do 04.09.": "1",
    "Fr 05.09.": "1",
    "Sa 06.09.": "1"
  },
  {
    "Stationsname": "Barth",
    "Di 02.09.": "2",
    "Mi 03.09.": "2",
    "Do 04.09.": "2",
    "Fr 05.09.": "2",
    "Sa 06.09.": "2"
  },
  {
    "Stationsname": "Steinhagen-Negast",
    "Di 02.09.": "2",
    "Mi 03.09.": "1",
    "Do 04.09.": "2",
    "Fr 05.09.": "1",
    "Sa 06.09.": "1"
  },
  {
    "Stationsname": "Greifswalder Oie",
    "Di 02.09.": "1",
    "Mi 03.09.": "1",
    "Do 04.09.": "1",
    "Fr 05.09.": "1",
    "Sa 06.09.": "1"
  },
  {
    "Stationsname": "Rostock-Warnemünde",
    "Di 02.09.": "2",
    "Mi 03.09.": "2",
    "Do 04.09.": "2",
    "Fr 05.09.": "1",
    "Sa 06.09.": "2"
  },
  {
    "Stationsname": "Karlshagen",
    "Di 02.09.": "1",
    "Mi 03.09.": "1",
    "Do 04.09.": "1",
    "Fr 05.09.": "1",
    "Sa 06.09.": "1"
  },
  {
    "Stationsname": "Greifswald",
    "Di 02.09.": "1",
    "Mi 03.09.": "1",
    "Do 04.09.": "2",
    "Fr 05.09.": "1",
    "Sa 06.09.": "1"
  },
  {
    "Stationsname": "Sanitz-Groß Lüsewitz",
    "Di 02.09.": "2",
    "Mi 03.09.": "2",
    "Do 04.09.": "2",
    "Fr 05.09.": "1",
    "Sa 06.09.": "1"
  },
  {
    "Stationsname": "Tribsees",
    "Di 02.09.": "2",
    "Mi 03.09.": "1",
    "Do 04.09.": "2",
    "Fr 05.09.": "1",
    "Sa 06.09.": "1"
  },
  {
    "Stationsname": "Boltenhagen",
    "Di 02.09.": "2",
    "Mi 03.09.": "2",
    "Do 04.09.": "2",
    "Fr 05.09.": "2",
    "Sa 06.09.": "2"
  },
  {
    "Stationsname": "Kirchdorf/Poel",
    "Di 02.09.": "2",
    "Mi 03.09.": "2",
    "Do 04.09.": "2",
    "Fr 05.09.": "1",
    "Sa 06.09.": "1"
  },
  {
    "Stationsname": "Laage-Kronskamp",
    "Di 02.09.": "1",
    "Mi 03.09.": "1",
    "Do 04.09.": "2",
    "Fr 05.09.": "2",
    "Sa 06.09.": "2"
  },
  {
    "Stationsname": "Anklam",
    "Di 02.09.": "1",
    "Mi 03.09.": "1",
    "Do 04.09.": "1",
    "Fr 05.09.": "1",
    "Sa 06.09.": "1"
  },
  {
    "Stationsname": "Gülzow-Prüzen",
    "Di 02.09.": "2",
    "Mi 03.09.": "2",
    "Do 04.09.": "2",
    "Fr 05.09.": "1",
    "Sa 06.09.": "1"
  },
  {
    "Stationsname": "Teterow",
    "Di 02.09.": "2",
    "Mi 03.09.": "1",
    "Do 04.09.": "2",
    "Fr 05.09.": "1",
    "Sa 06.09.": "1"
  },
  {
    "Stationsname": "Ueckermünde",
    "Di 02.09.": "1",
    "Mi 03.09.": "1",
    "Do 04.09.": "1",
    "Fr 05.09.": "1",
    "Sa 06.09.": "1"
  },
  {
    "Stationsname": "Schwerin",
    "Di 02.09.": "2",
    "Mi 03.09.": "2",
    "Do 04.09.": "1",
    "Fr 05.09.": "1",
    "Sa 06.09.": "1"
  },
  {
    "Stationsname": "Goldberg",
    "Di 02.09.": "2",
    "Mi 03.09.": "2",
    "Do 04.09.": "3",
    "Fr 05.09.": "1",
    "Sa 06.09.": "1"
  },
  {
    "Stationsname": "Trollenhagen",
    "Di 02.09.": "1",
    "Mi 03.09.": "1",
    "Do 04.09.": "2",
    "Fr 05.09.": "1",
    "Sa 06.09.": "1"
  },
  {
    "Stationsname": "Waren (Müritz)",
    "Di 02.09.": "1",
    "Mi 03.09.": "1",
    "Do 04.09.": "2",
    "Fr 05.09.": "1",
    "Sa 06.09.": "1"
  },
  {
    "Stationsname": "Boizenburg",
    "Di 02.09.": "2",
    "Mi 03.09.": "3",
    "Do 04.09.": "1",
    "Fr 05.09.": "2",
    "Sa 06.09.": "2"
  },
  {
    "Stationsname": "Grambow-Schwennenz",
    "Di 02.09.": "1",
    "Mi 03.09.": "1",
    "Do 04.09.": "1",
    "Fr 05.09.": "2",
    "Sa 06.09.": "1"
  },
  {
    "Stationsname": "Marnitz",
    "Di 02.09.": "2",
    "Mi 03.09.": "2",
    "Do 04.09.": "3",
    "Fr 05.09.": "1",
    "Sa 06.09.": "1"
  },
  {
    "Stationsname": "Feldberg/Mecklenburg",
    "Di 02.09.": "1",
    "Mi 03.09.": "1",
    "Do 04.09.": "1",
    "Fr 05.09.": "1",
    "Sa 06.09.": "1"
  }
]