[
  {
    "Stationsname": "Grünow",
    "Di 23.09.": "2",
    "Mi 24.09.": "2",
    "Do 25.09.": "2",
    "Fr 26.09.": "2",
    "Sa 27.09.": "2"
  },
  {
    "Stationsname": "Wittstock-Rote Mühle",
    "Di 23.09.": "1",
    "Mi 24.09.": "2",
    "Do 25.09.": "3",
    "Fr 26.09.": "3",
    "Sa 27.09.": "2"
  },
  {
    "Stationsname": "Stechlin-Menz",
    "Di 23.09.": "1",
    "Mi 24.09.": "2",
    "Do 25.09.": "2",
    "Fr 26.09.": "2",
    "Sa 27.09.": "2"
  },
  {
    "Stationsname": "Lenzen/Elbe",
    "Di 23.09.": "1",
    "Mi 24.09.": "1",
    "Do 25.09.": "2",
    "Fr 26.09.": "2",
    "Sa 27.09.": "2"
  },
  {
    "Stationsname": "Angermünde",
    "Di 23.09.": "2",
    "Mi 24.09.": "2",
    "Do 25.09.": "2",
    "Fr 26.09.": "3",
    "Sa 27.09.": "2"
  },
  {
    "Stationsname": "Zehdenick",
    "Di 23.09.": "2",
    "Mi 24.09.": "2",
    "Do 25.09.": "2",
    "Fr 26.09.": "2",
    "Sa 27.09.": "2"
  },
  {
    "Stationsname": "Neuruppin-Alt Ruppin",
    "Di 23.09.": "1",
    "Mi 24.09.": "2",
    "Do 25.09.": "2",
    "Fr 26.09.": "2",
    "Sa 27.09.": "2"
  },
  {
    "Stationsname": "Kyritz",
    "Di 23.09.": "1",
    "Mi 24.09.": "2",
    "Do 25.09.": "3",
    "Fr 26.09.": "3",
    "Sa 27.09.": "2"
  },
  {
    "Stationsname": "Heckelberg",
    "Di 23.09.": "1",
    "Mi 24.09.": "1",
    "Do 25.09.": "1",
    "Fr 26.09.": "2",
    "Sa 27.09.": "2"
  },
  {
    "Stationsname": "Berge",
    "Di 23.09.": "1",
    "Mi 24.09.": "2",
    "Do 25.09.": "2",
    "Fr 26.09.": "2",
    "Sa 27.09.": "2"
  },
  {
    "Stationsname": "Manschnow",
    "Di 23.09.": "1",
    "Mi 24.09.": "1",
    "Do 25.09.": "1",
    "Fr 26.09.": "2",
    "Sa 27.09.": "2"
  },
  {
    "Stationsname": "Müncheberg",
    "Di 23.09.": "1",
    "Mi 24.09.": "1",
    "Do 25.09.": "1",
    "Fr 26.09.": "2",
    "Sa 27.09.": "2"
  },
  {
    "Stationsname": "Potsdam",
    "Di 23.09.": "1",
    "Mi 24.09.": "2",
    "Do 25.09.": "2",
    "Fr 26.09.": "2",
    "Sa 27.09.": "2"
  },
  {
    "Stationsname": "Berlin Brandenburg (Flughafen)",
    "Di 23.09.": "1",
    "Mi 24.09.": "1",
    "Do 25.09.": "2",
    "Fr 26.09.": "2",
    "Sa 27.09.": "2"
  },
  {
    "Stationsname": "Wusterwitz",
    "Di 23.09.": "2",
    "Mi 24.09.": "2",
    "Do 25.09.": "3",
    "Fr 26.09.": "2",
    "Sa 27.09.": "2"
  },
  {
    "Stationsname": "Lindenberg",
    "Di 23.09.": "1",
    "Mi 24.09.": "1",
    "Do 25.09.": "1",
    "Fr 26.09.": "1",
    "Sa 27.09.": "2"
  },
  {
    "Stationsname": "Wiesenburg",
    "Di 23.09.": "1",
    "Mi 24.09.": "1",
    "Do 25.09.": "2",
    "Fr 26.09.": "2",
    "Sa 27.09.": "2"
  },
  {
    "Stationsname": "Baruth",
    "Di 23.09.": "1",
    "Mi 24.09.": "1",
    "Do 25.09.": "1",
    "Fr 26.09.": "1",
    "Sa 27.09.": "1"
  },
  {
    "Stationsname": "Coschen",
    "Di 23.09.": "1",
    "Mi 24.09.": "1",
    "Do 25.09.": "1",
    "Fr 26.09.": "1",
    "Sa 27.09.": "2"
  },
  {
    "Stationsname": "Lübben-Blumenfelde",
    "Di 23.09.": "1",
    "Mi 24.09.": "1",
    "Do 25.09.": "1",
    "Fr 26.09.": "1",
    "Sa 27.09.": "1"
  },
  {
    "Stationsname": "Langenlipsdorf",
    "Di 23.09.": "1",
    "Mi 24.09.": "1",
    "Do 25.09.": "1",
    "Fr 26.09.": "2",
    "Sa 27.09.": "2"
  },
  {
    "Stationsname": "Cottbus",
    "Di 23.09.": "1",
    "Mi 24.09.": "1",
    "Do 25.09.": "1",
    "Fr 26.09.": "1",
    "Sa 27.09.": "1"
  },
  {
    "Stationsname": "Holzdorf-Bernsdorf",
    "Di 23.09.": "1",
    "Mi 24.09.": "1",
    "Do 25.09.": "1",
    "Fr 26.09.": "1",
    "Sa 27.09.": "1"
  },
  {
    "Stationsname": "Doberlug-Kirchhain",
    "Di 23.09.": "1",
    "Mi 24.09.": "1",
    "Do 25.09.": "1",
    "Fr 26.09.": "1",
    "Sa 27.09.": "1"
  },
  {
    "Stationsname": "Schipkau-Klettwitz",
    "Di 23.09.": "1",
    "Mi 24.09.": "1",
    "Do 25.09.": "1",
    "Fr 26.09.": "1",
    "Sa 27.09.": "1"
  }
]