[
  {
    "Stationsname": "Seehausen",
    "Di 31.03.": "1",
    "Mi 01.04.": "1",
    "Do 02.04.": "1",
    "Fr 03.04.": "2",
    "Sa 04.04.": "3"
  },
  {
    "Stationsname": "Gardelegen",
    "Di 31.03.": "1",
    "Mi 01.04.": "1",
    "Do 02.04.": "1",
    "Fr 03.04.": "2",
    "Sa 04.04.": "3"
  },
  {
    "Stationsname": "Demker",
    "Di 31.03.": "1",
    "Mi 01.04.": "1",
    "Do 02.04.": "1",
    "Fr 03.04.": "2",
    "Sa 04.04.": "3"
  },
  {
    "Stationsname": "Genthin",
    "Di 31.03.": "1",
    "Mi 01.04.": "1",
    "Do 02.04.": "1",
    "Fr 03.04.": "2",
    "Sa 04.04.": "3"
  },
  {
    "Stationsname": "Möckern-Drewitz",
    "Di 31.03.": "1",
    "Mi 01.04.": "1",
    "Do 02.04.": "1",
    "Fr 03.04.": "2",
    "Sa 04.04.": "3"
  },
  {
    "Stationsname": "Ummendorf",
    "Di 31.03.": "1",
    "Mi 01.04.": "1",
    "Do 02.04.": "1",
    "Fr 03.04.": "2",
    "Sa 04.04.": "3"
  },
  {
    "Stationsname": "Magdeburg",
    "Di 31.03.": "1",
    "Mi 01.04.": "1",
    "Do 02.04.": "1",
    "Fr 03.04.": "1",
    "Sa 04.04.": "2"
  },
  {
    "Stationsname": "Huy-Pabstorf",
    "Di 31.03.": "1",
    "Mi 01.04.": "1",
    "Do 02.04.": "1",
    "Fr 03.04.": "2",
    "Sa 04.04.": "3"
  },
  {
    "Stationsname": "Wittenberg",
    "Di 31.03.": "1",
    "Mi 01.04.": "1",
    "Do 02.04.": "1",
    "Fr 03.04.": "1",
    "Sa 04.04.": "2"
  },
  {
    "Stationsname": "Wernigerode",
    "Di 31.03.": "1",
    "Mi 01.04.": "1",
    "Do 02.04.": "1",
    "Fr 03.04.": "2",
    "Sa 04.04.": "3"
  },
  {
    "Stationsname": "Bernburg/Saale",
    "Di 31.03.": "1",
    "Mi 01.04.": "1",
    "Do 02.04.": "1",
    "Fr 03.04.": "1",
    "Sa 04.04.": "2"
  },
  {
    "Stationsname": "Quedlinburg",
    "Di 31.03.": "1",
    "Mi 01.04.": "1",
    "Do 02.04.": "1",
    "Fr 03.04.": "2",
    "Sa 04.04.": "3"
  },
  {
    "Stationsname": "Wernigerode-Schierke",
    "Di 31.03.": "1",
    "Mi 01.04.": "1",
    "Do 02.04.": "1",
    "Fr 03.04.": "1",
    "Sa 04.04.": "1"
  },
  {
    "Stationsname": "Köthen (Anhalt)",
    "Di 31.03.": "1",
    "Mi 01.04.": "1",
    "Do 02.04.": "1",
    "Fr 03.04.": "1",
    "Sa 04.04.": "2"
  },
  {
    "Stationsname": "Aschersleben-Mehringen",
    "Di 31.03.": "1",
    "Mi 01.04.": "1",
    "Do 02.04.": "1",
    "Fr 03.04.": "1",
    "Sa 04.04.": "2"
  },
  {
    "Stationsname": "Jeßnitz",
    "Di 31.03.": "1",
    "Mi 01.04.": "1",
    "Do 02.04.": "1",
    "Fr 03.04.": "1",
    "Sa 04.04.": "2"
  },
  {
    "Stationsname": "Oberharz am Brocken-Stiege",
    "Di 31.03.": "1",
    "Mi 01.04.": "1",
    "Do 02.04.": "1",
    "Fr 03.04.": "1",
    "Sa 04.04.": "2"
  },
  {
    "Stationsname": "Harzgerode",
    "Di 31.03.": "1",
    "Mi 01.04.": "1",
    "Do 02.04.": "1",
    "Fr 03.04.": "2",
    "Sa 04.04.": "3"
  },
  {
    "Stationsname": "Bad Lauchstädt",
    "Di 31.03.": "1",
    "Mi 01.04.": "1",
    "Do 02.04.": "1",
    "Fr 03.04.": "1",
    "Sa 04.04.": "3"
  },
  {
    "Stationsname": "Querfurt-Lodersleben",
    "Di 31.03.": "1",
    "Mi 01.04.": "1",
    "Do 02.04.": "1",
    "Fr 03.04.": "1",
    "Sa 04.04.": "3"
  },
  {
    "Stationsname": "Naumburg-Kreipitzsch/Saale",
    "Di 31.03.": "1",
    "Mi 01.04.": "1",
    "Do 02.04.": "1",
    "Fr 03.04.": "1",
    "Sa 04.04.": "2"
  },
  {
    "Stationsname": "Osterfeld",
    "Di 31.03.": "1",
    "Mi 01.04.": "1",
    "Do 02.04.": "1",
    "Fr 03.04.": "1",
    "Sa 04.04.": "2"
  },
  {
    "Stationsname": "Zeitz",
    "Di 31.03.": "1",
    "Mi 01.04.": "1",
    "Do 02.04.": "1",
    "Fr 03.04.": "1",
    "Sa 04.04.": "2"
  }
]