[
  {
    "Stationsname": "Seehausen",
    "So 05.10.": "1",
    "Mo 06.10.": "1",
    "Di 07.10.": "1",
    "Mi 08.10.": "1",
    "Do 09.10.": "1"
  },
  {
    "Stationsname": "Gardelegen",
    "So 05.10.": "1",
    "Mo 06.10.": "1",
    "Di 07.10.": "1",
    "Mi 08.10.": "1",
    "Do 09.10.": "1"
  },
  {
    "Stationsname": "Demker",
    "So 05.10.": "1",
    "Mo 06.10.": "1",
    "Di 07.10.": "1",
    "Mi 08.10.": "1",
    "Do 09.10.": "1"
  },
  {
    "Stationsname": "Genthin",
    "So 05.10.": "1",
    "Mo 06.10.": "1",
    "Di 07.10.": "1",
    "Mi 08.10.": "1",
    "Do 09.10.": "1"
  },
  {
    "Stationsname": "Möckern-Drewitz",
    "So 05.10.": "1",
    "Mo 06.10.": "1",
    "Di 07.10.": "1",
    "Mi 08.10.": "1",
    "Do 09.10.": "1"
  },
  {
    "Stationsname": "Ummendorf",
    "So 05.10.": "1",
    "Mo 06.10.": "1",
    "Di 07.10.": "1",
    "Mi 08.10.": "1",
    "Do 09.10.": "1"
  },
  {
    "Stationsname": "Magdeburg",
    "So 05.10.": "1",
    "Mo 06.10.": "2",
    "Di 07.10.": "1",
    "Mi 08.10.": "1",
    "Do 09.10.": "1"
  },
  {
    "Stationsname": "Huy-Pabstorf",
    "So 05.10.": "1",
    "Mo 06.10.": "1",
    "Di 07.10.": "1",
    "Mi 08.10.": "1",
    "Do 09.10.": "1"
  },
  {
    "Stationsname": "Wittenberg",
    "So 05.10.": "1",
    "Mo 06.10.": "1",
    "Di 07.10.": "1",
    "Mi 08.10.": "1",
    "Do 09.10.": "1"
  },
  {
    "Stationsname": "Wernigerode",
    "So 05.10.": "1",
    "Mo 06.10.": "1",
    "Di 07.10.": "1",
    "Mi 08.10.": "1",
    "Do 09.10.": "1"
  },
  {
    "Stationsname": "Bernburg/Saale",
    "So 05.10.": "1",
    "Mo 06.10.": "2",
    "Di 07.10.": "1",
    "Mi 08.10.": "1",
    "Do 09.10.": "1"
  },
  {
    "Stationsname": "Quedlinburg",
    "So 05.10.": "2",
    "Mo 06.10.": "2",
    "Di 07.10.": "1",
    "Mi 08.10.": "1",
    "Do 09.10.": "1"
  },
  {
    "Stationsname": "Wernigerode-Schierke",
    "So 05.10.": "1",
    "Mo 06.10.": "1",
    "Di 07.10.": "1",
    "Mi 08.10.": "1",
    "Do 09.10.": "1"
  },
  {
    "Stationsname": "Köthen (Anhalt)",
    "So 05.10.": "1",
    "Mo 06.10.": "1",
    "Di 07.10.": "1",
    "Mi 08.10.": "1",
    "Do 09.10.": "1"
  },
  {
    "Stationsname": "Aschersleben-Mehringen",
    "So 05.10.": "1",
    "Mo 06.10.": "2",
    "Di 07.10.": "1",
    "Mi 08.10.": "1",
    "Do 09.10.": "1"
  },
  {
    "Stationsname": "Jeßnitz",
    "So 05.10.": "1",
    "Mo 06.10.": "1",
    "Di 07.10.": "1",
    "Mi 08.10.": "1",
    "Do 09.10.": "1"
  },
  {
    "Stationsname": "Oberharz am Brocken-Stiege",
    "So 05.10.": "1",
    "Mo 06.10.": "1",
    "Di 07.10.": "1",
    "Mi 08.10.": "1",
    "Do 09.10.": "1"
  },
  {
    "Stationsname": "Harzgerode",
    "So 05.10.": "1",
    "Mo 06.10.": "1",
    "Di 07.10.": "1",
    "Mi 08.10.": "1",
    "Do 09.10.": "1"
  },
  {
    "Stationsname": "Bad Lauchstädt",
    "So 05.10.": "1",
    "Mo 06.10.": "1",
    "Di 07.10.": "1",
    "Mi 08.10.": "1",
    "Do 09.10.": "1"
  },
  {
    "Stationsname": "Querfurt-Lodersleben",
    "So 05.10.": "1",
    "Mo 06.10.": "1",
    "Di 07.10.": "1",
    "Mi 08.10.": "1",
    "Do 09.10.": "1"
  },
  {
    "Stationsname": "Naumburg-Kreipitzsch/Saale",
    "So 05.10.": "1",
    "Mo 06.10.": "1",
    "Di 07.10.": "1",
    "Mi 08.10.": "1",
    "Do 09.10.": "1"
  },
  {
    "Stationsname": "Osterfeld",
    "So 05.10.": "1",
    "Mo 06.10.": "1",
    "Di 07.10.": "1",
    "Mi 08.10.": "1",
    "Do 09.10.": "1"
  },
  {
    "Stationsname": "Zeitz",
    "So 05.10.": "1",
    "Mo 06.10.": "1",
    "Di 07.10.": "1",
    "Mi 08.10.": "1",
    "Do 09.10.": "1"
  }
]